tokens/__init__.py
tokens/admin.py
tokens/apps.py
tokens/models.py
tokens/tests.py
tokens/views.py
tokens/migrations/0001_initial.py
tokens/migrations/0002_multitoken_user.py
tokens/migrations/__init__.py
django_multi_token-0.1.5.dist-info/METADATA
django_multi_token-0.1.5.dist-info/WHEEL
django_multi_token-0.1.5.dist-info/entry_points.txt
django_multi_token-0.1.5.dist-info/top_level.txt
django_multi_token-0.1.5.dist-info/RECORD
