Metadata-Version: 2.1
Name: django-multi-token
Version: 0.1.5
Summary: Multi token for django rest framework
Home-page: https://github.com/Raja27/multi-token.git
Author: MRP DevShort
Author-email: mrppythondev@gmail.com
License: MIT
Keywords: django multi token,token,dajngo rest framework multi token
Platform: UNKNOWN
Classifier: Development Status :: 5 - Production/Stable
Classifier: Intended Audience :: Developers
Classifier: Topic :: Software Development :: Build Tools
Classifier: License :: OSI Approved :: MIT License
Classifier: Programming Language :: Python :: 3.4
Classifier: Programming Language :: Python :: 3.5
Classifier: Programming Language :: Python :: 3.7
Classifier: Programming Language :: Python :: 3.8
Classifier: Programming Language :: Python :: 3.9
Classifier: Programming Language :: Python :: 3.10
Requires-Dist: django
Requires-Dist: djangorestframework
Provides-Extra: dev
Requires-Dist: check-manifest ; extra == 'dev'
Provides-Extra: test
Requires-Dist: coverage ; extra == 'test'
